cloudshell/__init__.py
cloudshell/cp/__init__.py
cloudshell/cp/azure/__init__.py
cloudshell/cp/azure/azure_client.py
cloudshell/cp/azure/constants.py
cloudshell/cp/azure/exceptions.py
cloudshell/cp/azure/request_actions.py
cloudshell/cp/azure/reservation_info.py
cloudshell/cp/azure/resource_config.py
cloudshell/cp/azure/actions/__init__.py
cloudshell/cp/azure/actions/network.py
cloudshell/cp/azure/actions/network_security_group.py
cloudshell/cp/azure/actions/resource_group.py
cloudshell/cp/azure/actions/route_tables.py
cloudshell/cp/azure/actions/ssh_key_pair.py
cloudshell/cp/azure/actions/storage_account.py
cloudshell/cp/azure/actions/validation.py
cloudshell/cp/azure/actions/vm.py
cloudshell/cp/azure/actions/vm_credentials.py
cloudshell/cp/azure/actions/vm_details.py
cloudshell/cp/azure/actions/vm_extension.py
cloudshell/cp/azure/actions/vm_image.py
cloudshell/cp/azure/flows/__init__.py
cloudshell/cp/azure/flows/access_key.py
cloudshell/cp/azure/flows/app_security_groups.py
cloudshell/cp/azure/flows/application_ports.py
cloudshell/cp/azure/flows/autoload.py
cloudshell/cp/azure/flows/available_ip.py
cloudshell/cp/azure/flows/cleanup.py
cloudshell/cp/azure/flows/create_route_tables.py
cloudshell/cp/azure/flows/delete_instance.py
cloudshell/cp/azure/flows/power_mgmt.py
cloudshell/cp/azure/flows/refresh_ip.py
cloudshell/cp/azure/flows/vm_details.py
cloudshell/cp/azure/flows/deploy_vm/__init__.py
cloudshell/cp/azure/flows/deploy_vm/base_flow.py
cloudshell/cp/azure/flows/deploy_vm/deploy_custom_vm.py
cloudshell/cp/azure/flows/deploy_vm/deploy_marketplace_vm.py
cloudshell/cp/azure/flows/deploy_vm/deploy_shared_gallery_vm.py
cloudshell/cp/azure/flows/deploy_vm/commands/__init__.py
cloudshell/cp/azure/flows/deploy_vm/commands/create_allow_additional_mgmt_network_rule.py
cloudshell/cp/azure/flows/deploy_vm/commands/create_allow_mgmt_vnet_rule.py
cloudshell/cp/azure/flows/deploy_vm/commands/create_allow_sandbox_inbound_port_rule.py
cloudshell_cp_azure-4.0.1.1.dist-info/METADATA
cloudshell_cp_azure-4.0.1.1.dist-info/WHEEL
cloudshell_cp_azure-4.0.1.1.dist-info/top_level.txt
cloudshell_cp_azure-4.0.1.1.dist-info/RECORD
