Metadata-Version: 2.1
Name: cloudshell-cp-azure
Version: 4.0.1.1
Summary: This Shell enables setting up Azure as a cloud provider in CloudShell. It supports connectivity, and adds new deployment types for apps which can be used in CloudShell sandboxes.
Home-page: http://www.qualisystems.com/
Author: QualiSystems
Author-email: info@qualisystems.com
Requires-Python: ~=3.7
Requires-Dist: cloudshell-shell-core (<6.0.0,>=5.0.3)
Requires-Dist: cloudshell-cp-core (<3.0.0,>=2.5.4)
Requires-Dist: cloudshell-shell-standards (<2.0,>=1.0)
Requires-Dist: cloudshell-shell-flows (<2,>=1.0)
Requires-Dist: cloudshell-automation-api (<2020.2.0.180455,>=9.2)
Requires-Dist: azure-core (~=1.26)
Requires-Dist: azure-identity (~=1.11)
Requires-Dist: azure-keyvault-secrets (~=4.6)
Requires-Dist: azure-mgmt-resource (~=21.1)
Requires-Dist: azure-mgmt-compute (~=28.0)
Requires-Dist: azure-mgmt-network (~=21.0)
Requires-Dist: azure-mgmt-storage (~=20.1)
Requires-Dist: azure-storage (==0.36.0)
Requires-Dist: deprecation
Requires-Dist: netaddr (==0.7.19)
Requires-Dist: requests (==2.26.0)
Requires-Dist: msrest (==0.7.1)
Requires-Dist: msrestazure (==0.6.4)
Requires-Dist: retrying (==1.3.3)
Requires-Dist: urllib3 (==1.25.8)
